chinese_stroke_sorting/__init__.py
chinese_stroke_sorting/bh.txt
chinese_stroke_sorting/chinese_stroke_sorting.py
chinese_stroke_sorting/chinese_stroke_sorting_test.py
chinese_stroke_sorting-0.3.1.dist-info/LICENSE
chinese_stroke_sorting-0.3.1.dist-info/METADATA
chinese_stroke_sorting-0.3.1.dist-info/WHEEL
chinese_stroke_sorting-0.3.1.dist-info/top_level.txt
chinese_stroke_sorting-0.3.1.dist-info/RECORD
