Metadata-Version: 2.1
Name: chinese-stroke-sorting
Version: 0.3.1
Summary: Chinese Name Sort by Stroke Order
Home-page: https://github.com/echosun1996/ChineseStrokeSorting
Author: echosun
Author-email: echosun1996@126.com
License: UNKNOWN
Platform: UNKNOWN
Classifier: Programming Language :: Python :: 3
Classifier: Programming Language :: Python :: 3.5
Classifier: Programming Language :: Python :: 3.6
Classifier: Programming Language :: Python :: 3.7
Classifier: Programming Language :: Python :: 3.8
Classifier: License :: OSI Approved :: GNU General Public License v3 (GPLv3)
Classifier: Operating System :: OS Independent
Classifier: Topic :: Text Processing
Requires-Python: >=3.5
